Etapa2/Probador_arbitro2.v
module Probador_arbitro2 #(
    parameter WORD_SIZE = 12
    //parameter FIFO_UNITS = 4
) (
   
    output reg clk,
    output reg reset,
    output reg [WORD_SIZE-1:0] data_in_arb,
    output reg fifo_empty,
    output reg [3:0] fifos_almost_full,
    input [WORD_SIZE-1:0] data_out_arb,
    input [WORD_SIZE-1:0] data_out_arb_sint,
    input pop,
    input pop_sint,
    input [3:0] push,
    input [3:0] push_sint
);
    initial clk = 0;
    always #1 clk = ~clk;

    initial begin
        $dumpfile ("arbitro2.vcd");
        $dumpvars;
        
        // Inicio de la simulación
        reset <= 0;
        data_in_arb <= 0; 
        fifo_empty <=0;
        fifos_almost_full <= 0;

        // Se desactiva el reset
        @(posedge clk);
        reset <= 1;
        data_in_arb <= 12'b111011100011; 

        @(posedge clk);
        data_in_arb <= 12'b001011100011; 
        fifo_empty <= 0;
        fifos_almost_full <= 0;

        @(posedge clk);
        data_in_arb <= 12'b110011110011; 
      
        @(posedge clk);
        data_in_arb <= 12'b100000110001;  

        @(posedge clk);
        data_in_arb <= 12'b011110111101;
        
        @(posedge clk);
        data_in_arb <= 12'b111111111101;

        @(posedge clk);
        fifo_empty <= 1;

        @(posedge clk);
        data_in_arb <= 12'b011111111101;
        
        @(posedge clk);
        fifo_empty <= 0;
        data_in_arb <= 12'b001110011101;
        fifos_almost_full <= 4'b0001;

        
        @(posedge clk);
        data_in_arb <= 12'b111110001101;
        fifos_almost_full <= 4'b1000;

        @(posedge clk);
        data_in_arb <= 12'b011110011101;
        fifos_almost_full <= 4'b0010;

        @(posedge clk);
        data_in_arb <= 12'b100110111011;
        fifos_almost_full <= 4'b0100;
        
        @(posedge clk);
        data_in_arb <= 12'b100110111011;
        fifos_almost_full <= 4'b1111;
        
        @(posedge clk);
        @(posedge clk);
        @(posedge clk);
        $finish;
    end
endmodule

Etapa2/arbitro2_sint.v
/* Generated by Yosys 0.9 (git sha1 1979e0b) */

(* dynports =  1  *)
(* top =  1  *)
(* src = "arbitro2_sint.v:1" *)
module arbitro2_sint(clk, reset, data_in_arb, fifo_empty, fifos_almost_full, data_out_arb_sint, pop_sint, push_sint);
  (* src = "arbitro2_sint.v:17" *)
  wire [11:0] _00_;
  (* src = "arbitro2_sint.v:17" *)
  wire _01_;
  (* src = "arbitro2_sint.v:17" *)
  wire [3:0] _02_;
  wire _03_;
  wire _04_;
  wire _05_;
  wire _06_;
  wire _07_;
  wire _08_;
  wire _09_;
  wire _10_;
  wire _11_;
  wire _12_;
  wire _13_;
  wire _14_;
  wire _15_;
  wire _16_;
  wire _17_;
  wire _18_;
  wire _19_;
  wire _20_;
  wire _21_;
  wire _22_;
  wire _23_;
  (* src = "arbitro2_sint.v:15" *)
  wire [1:0] \class ;
  (* src = "arbitro2_sint.v:6" *)
  input clk;
  (* src = "arbitro2_sint.v:8" *)
  input [11:0] data_in_arb;
  (* src = "arbitro2_sint.v:11" *)
  output [11:0] data_out_arb_sint;
  (* src = "arbitro2_sint.v:9" *)
  input fifo_empty;
  (* src = "arbitro2_sint.v:10" *)
  input [3:0] fifos_almost_full;
  (* src = "arbitro2_sint.v:12" *)
  output pop_sint;
  (* src = "arbitro2_sint.v:13" *)
  output [3:0] push_sint;
  (* src = "arbitro2_sint.v:7" *)
  input reset;
  NOT _24_ (
    .A(data_in_arb[11]),
    .Y(_03_)
  );
  NOT _25_ (
    .A(fifo_empty),
    .Y(_04_)
  );
  NOT _26_ (
    .A(data_in_arb[0]),
    .Y(_05_)
  );
  NOT _27_ (
    .A(data_in_arb[1]),
    .Y(_06_)
  );
  NOT _28_ (
    .A(data_in_arb[2]),
    .Y(_07_)
  );
  NOT _29_ (
    .A(data_in_arb[3]),
    .Y(_08_)
  );
  NOT _30_ (
    .A(data_in_arb[4]),
    .Y(_09_)
  );
  NOT _31_ (
    .A(data_in_arb[5]),
    .Y(_10_)
  );
  NOT _32_ (
    .A(data_in_arb[6]),
    .Y(_11_)
  );
  NOT _33_ (
    .A(data_in_arb[7]),
    .Y(_12_)
  );
  NOT _34_ (
    .A(data_in_arb[8]),
    .Y(_13_)
  );
  NOT _35_ (
    .A(data_in_arb[9]),
    .Y(_14_)
  );
  NAND _36_ (
    .A(pop_sint),
    .B(reset),
    .Y(_15_)
  );
  NOT _37_ (
    .A(_15_),
    .Y(_16_)
  );
  NAND _38_ (
    .A(data_in_arb[10]),
    .B(_16_),
    .Y(_17_)
  );
  NOT _39_ (
    .A(_17_),
    .Y(_00_[10])
  );
  NAND _40_ (
    .A(data_in_arb[11]),
    .B(_16_),
    .Y(_18_)
  );
  NOT _41_ (
    .A(_18_),
    .Y(_00_[11])
  );
  NOR _42_ (
    .A(_03_),
    .B(_17_),
    .Y(_02_[3])
  );
  NOR _43_ (
    .A(data_in_arb[10]),
    .B(_18_),
    .Y(_02_[2])
  );
  NOR _44_ (
    .A(data_in_arb[11]),
    .B(_17_),
    .Y(_02_[1])
  );
  NAND _45_ (
    .A(_03_),
    .B(_16_),
    .Y(_19_)
  );
  NOR _46_ (
    .A(data_in_arb[10]),
    .B(_19_),
    .Y(_02_[0])
  );
  NAND _47_ (
    .A(reset),
    .B(_04_),
    .Y(_20_)
  );
  NOR _48_ (
    .A(fifos_almost_full[3]),
    .B(fifos_almost_full[2]),
    .Y(_21_)
  );
  NOR _49_ (
    .A(fifos_almost_full[1]),
    .B(fifos_almost_full[0]),
    .Y(_22_)
  );
  NAND _50_ (
    .A(_21_),
    .B(_22_),
    .Y(_23_)
  );
  NOR _51_ (
    .A(_20_),
    .B(_23_),
    .Y(_01_)
  );
  NOR _52_ (
    .A(_05_),
    .B(_15_),
    .Y(_00_[0])
  );
  NOR _53_ (
    .A(_06_),
    .B(_15_),
    .Y(_00_[1])
  );
  NOR _54_ (
    .A(_07_),
    .B(_15_),
    .Y(_00_[2])
  );
  NOR _55_ (
    .A(_08_),
    .B(_15_),
    .Y(_00_[3])
  );
  NOR _56_ (
    .A(_09_),
    .B(_15_),
    .Y(_00_[4])
  );
  NOR _57_ (
    .A(_10_),
    .B(_15_),
    .Y(_00_[5])
  );
  NOR _58_ (
    .A(_11_),
    .B(_15_),
    .Y(_00_[6])
  );
  NOR _59_ (
    .A(_12_),
    .B(_15_),
    .Y(_00_[7])
  );
  NOR _60_ (
    .A(_13_),
    .B(_15_),
    .Y(_00_[8])
  );
  NOR _61_ (
    .A(_14_),
    .B(_15_),
    .Y(_00_[9])
  );
  (* src = "arbitro2_sint.v:17" *)
  DFF _62_ (
    .C(clk),
    .D(_00_[0]),
    .Q(data_out_arb_sint[0])
  );
  (* src = "arbitro2_sint.v:17" *)
  DFF _63_ (
    .C(clk),
    .D(_00_[1]),
    .Q(data_out_arb_sint[1])
  );
  (* src = "arbitro2_sint.v:17" *)
  DFF _64_ (
    .C(clk),
    .D(_00_[2]),
    .Q(data_out_arb_sint[2])
  );
  (* src = "arbitro2_sint.v:17" *)
  DFF _65_ (
    .C(clk),
    .D(_00_[3]),
    .Q(data_out_arb_sint[3])
  );
  (* src = "arbitro2_sint.v:17" *)
  DFF _66_ (
    .C(clk),
    .D(_00_[4]),
    .Q(data_out_arb_sint[4])
  );
  (* src = "arbitro2_sint.v:17" *)
  DFF _67_ (
    .C(clk),
    .D(_00_[5]),
    .Q(data_out_arb_sint[5])
  );
  (* src = "arbitro2_sint.v:17" *)
  DFF _68_ (
    .C(clk),
    .D(_00_[6]),
    .Q(data_out_arb_sint[6])
  );
  (* src = "arbitro2_sint.v:17" *)
  DFF _69_ (
    .C(clk),
    .D(_00_[7]),
    .Q(data_out_arb_sint[7])
  );
  (* src = "arbitro2_sint.v:17" *)
  DFF _70_ (
    .C(clk),
    .D(_00_[8]),
    .Q(data_out_arb_sint[8])
  );
  (* src = "arbitro2_sint.v:17" *)
  DFF _71_ (
    .C(clk),
    .D(_00_[9]),
    .Q(data_out_arb_sint[9])
  );
  (* src = "arbitro2_sint.v:17" *)
  DFF _72_ (
    .C(clk),
    .D(_00_[10]),
    .Q(data_out_arb_sint[10])
  );
  (* src = "arbitro2_sint.v:17" *)
  DFF _73_ (
    .C(clk),
    .D(_00_[11]),
    .Q(data_out_arb_sint[11])
  );
  (* src = "arbitro2_sint.v:17" *)
  DFF _74_ (
    .C(clk),
    .D(_01_),
    .Q(pop_sint)
  );
  (* src = "arbitro2_sint.v:17" *)
  DFF _75_ (
    .C(clk),
    .D(_02_[0]),
    .Q(push_sint[0])
  );
  (* src = "arbitro2_sint.v:17" *)
  DFF _76_ (
    .C(clk),
    .D(_02_[1]),
    .Q(push_sint[1])
  );
  (* src = "arbitro2_sint.v:17" *)
  DFF _77_ (
    .C(clk),
    .D(_02_[2]),
    .Q(push_sint[2])
  );
  (* src = "arbitro2_sint.v:17" *)
  DFF _78_ (
    .C(clk),
    .D(_02_[3]),
    .Q(push_sint[3])
  );
  assign \class  = data_in_arb[11:10];
endmodule

Etapa2/arbitro2.v
module arbitro2 #(
	// Tamaño de cada celda de memoria, [11:10] clase [9:8] destino [7:0] datos
    parameter WORD_SIZE = 12

) (
    input clk,
    input reset,
    input [WORD_SIZE-1:0] data_in_arb,
    input fifo_empty,
    input [3:0] fifos_almost_full,
    output reg [WORD_SIZE-1:0] data_out_arb,
    output reg pop,
    output reg [3:0] push
);
    reg [1:0] class;

    always @(posedge clk) begin
        if (!reset) begin
            pop <= 0;
            push <= 0;
            data_out_arb <= 0;
        end
        else begin
            if (fifo_empty) begin
                pop <= 0;
                push <= 0;
                data_out_arb <= 0;
            end
            else begin
                if (fifos_almost_full[3] | fifos_almost_full[2] | fifos_almost_full[1] | fifos_almost_full[0]) begin
                    pop <= 0;
                    push <= 0;
                    data_out_arb <= 0;
                end
                else begin
                    pop <= 1;
                    push <= 0;
                end
            end
            if (pop) begin
                case (class)
                    2'b00: begin
                        push[0] <= 1;
                        data_out_arb <= data_in_arb;
                    end
                    2'b01: begin
                        push[1] <= 1;
                        data_out_arb <= data_in_arb;
                    end
                    2'b10: begin
                        push[2] <= 1;
                        data_out_arb <= data_in_arb;
                    end
                    2'b11: begin
                        push[3] <= 1;
                        data_out_arb <= data_in_arb;
                    end
                endcase
            end    
            else data_out_arb <= 0;
        end
    end

    always @(*) begin
        class = data_in_arb[WORD_SIZE-1:WORD_SIZE-2];
    end
endmodule

Etapa2/BancoPrueba_arbitro2.v
`timescale 1ns/1ns
`include "arbitro2.v"
`include "arbitro2_sint.v"
`include "cmos_cells.v"
`include "Probador_arbitro2.v"

module BancoPrueba_arbitro2();
    parameter WORD_SIZE = 12;
    //parameter FIFO_UNITS = 4;

    wire clk;
    wire reset;
    wire [WORD_SIZE-1:0] data_in_arb;
    wire fifo_empty;
    wire [3:0] fifos_almost_full;
    wire [WORD_SIZE-1:0] data_out_arb;
    wire [WORD_SIZE-1:0] data_out_arb_sint;
    wire pop;
    wire pop_sint;
    wire [3:0] push;
    wire [3:0] push_sint;
 

    arbitro2 #( .WORD_SIZE(WORD_SIZE)) arbitro_cond1 (
                                // entradas
                                .clk(clk),  
                                .reset(reset),
                                .data_in_arb(data_in_arb),
                                .fifo_empty(fifo_empty),
                                .fifos_almost_full(fifos_almost_full),

                                // salidas
                                .data_out_arb(data_out_arb),
                                .pop(pop),
                                .push(push));

    arbitro2_sint #(.WORD_SIZE(WORD_SIZE)) arbitro2_sint1 ( 
                                    // entradas
                                    .clk(clk),  
                                    .reset(reset),
                                    .data_in_arb(data_in_arb),
                                    .fifo_empty(fifo_empty),
                                    .fifos_almost_full(fifos_almost_full),
                                    // salidas 
                                    .data_out_arb_sint(data_out_arb_sint),
                                    .pop_sint(pop_sint),
                                    .push_sint(push_sint)
                                    );
                                   
    Probador_arbitro2 #(.WORD_SIZE(WORD_SIZE))  
                    Probador_arbitro21 (
                                        .clk(clk),  
                                        .reset(reset),
                                        .data_in_arb(data_in_arb),
                                        .fifo_empty(fifo_empty),
                                        .fifos_almost_full(fifos_almost_full),
                                        // salidas conductuales y escructurales
                                        .data_out_arb(data_out_arb),
                                        .pop(pop),
                                        .push(push),
                                        .data_out_arb_sint(data_out_arb_sint),
                                        .pop_sint(pop_sint));

// checker para cuenta, cuenta_sint, valid y 
reg [2:0] checker; 

always @(*) begin
    if (data_out_arb == data_out_arb_sint) checker[2] = 1;
    else checker[2] = 0;
    if (push == push_sint) checker[1] = 1;
	else checker[1] = 0;
    if (pop == pop_sint) checker[0] = 1;
    else checker[0] = 0;
	end

endmodule

Etapa2/cmos_cells.v
module BUF(A, Y);
input A;
output Y;
assign Y = A;
endmodule

module NOT(A, Y);
input A;
output Y;
assign Y = ~A;
endmodule

module NAND(A, B, Y);
input A, B;
output Y;
assign Y = ~(A & B);
endmodule

module NOR(A, B, Y);
input A, B;
output Y;
assign Y = ~(A | B);
endmodule

module DFF(C, D, Q);
input C, D;
output reg Q;
always @(posedge C)
	Q <= D;
endmodule

module DFFSR(C, D, Q, S, R);
input C, D, S, R;
output reg Q;
always @(posedge C, posedge S, posedge R)
	if (S)
		Q <= 1'b1;
	else if (R)
		Q <= 1'b0;
	else
		Q <= D;
endmodule

Etapa2/arbitro2.vcd
$date
	Thu Nov 18 21:31:19 2021
$end
$version
	Icarus Verilog
$end
$timescale
	1ns
$end
$scope module BUF $end
$var wire 1 ! A $end
$var wire 1 " Y $end
$upscope $end
$scope module BancoPrueba_arbitro2 $end
$var wire 1 # reset $end
$var wire 4 $ push_sint [3:0] $end
$var wire 4 % push [3:0] $end
$var wire 1 & pop_sint $end
$var wire 1 ' pop $end
$var wire 4 ( fifos_almost_full [3:0] $end
$var wire 1 ) fifo_empty $end
$var wire 12 * data_out_arb_sint [11:0] $end
$var wire 12 + data_out_arb [11:0] $end
$var wire 12 , data_in_arb [11:0] $end
$var wire 1 - clk $end
$var reg 3 . checker [2:0] $end
$scope module Probador_arbitro21 $end
$var wire 4 / push_sint [3:0] $end
$var wire 4 0 push [3:0] $end
$var wire 1 & pop_sint $end
$var wire 1 ' pop $end
$var wire 12 1 data_out_arb_sint [11:0] $end
$var wire 12 2 data_out_arb [11:0] $end
$var reg 1 - clk $end
$var reg 12 3 data_in_arb [11:0] $end
$var reg 1 ) fifo_empty $end
$var reg 4 4 fifos_almost_full [3:0] $end
$var reg 1 # reset $end
$upscope $end
$scope module arbitro2_sint1 $end
$var wire 1 - clk $end
$var wire 12 5 data_in_arb [11:0] $end
$var wire 1 ) fifo_empty $end
$var wire 4 6 fifos_almost_full [3:0] $end
$var wire 1 # reset $end
$var wire 4 7 push_sint [3:0] $end
$var wire 1 & pop_sint $end
$var wire 12 8 data_out_arb_sint [11:0] $end
$var wire 2 9 class [1:0] $end
$var wire 1 : _23_ $end
$var wire 1 ; _22_ $end
$var wire 1 < _21_ $end
$var wire 1 = _20_ $end
$var wire 1 > _19_ $end
$var wire 1 ? _18_ $end
$var wire 1 @ _17_ $end
$var wire 1 A _16_ $end
$var wire 1 B _15_ $end
$var wire 1 C _14_ $end
$var wire 1 D _13_ $end
$var wire 1 E _12_ $end
$var wire 1 F _11_ $end
$var wire 1 G _10_ $end
$var wire 1 H _09_ $end
$var wire 1 I _08_ $end
$var wire 1 J _07_ $end
$var wire 1 K _06_ $end
$var wire 1 L _05_ $end
$var wire 1 M _04_ $end
$var wire 1 N _03_ $end
$var wire 4 O _02_ [3:0] $end
$var wire 1 P _01_ $end
$var wire 12 Q _00_ [11:0] $end
$scope module _24_ $end
$var wire 1 R A $end
$var wire 1 N Y $end
$upscope $end
$scope module _25_ $end
$var wire 1 ) A $end
$var wire 1 M Y $end
$upscope $end
$scope module _26_ $end
$var wire 1 S A $end
$var wire 1 L Y $end
$upscope $end
$scope module _27_ $end
$var wire 1 T A $end
$var wire 1 K Y $end
$upscope $end
$scope module _28_ $end
$var wire 1 U A $end
$var wire 1 J Y $end
$upscope $end
$scope module _29_ $end
$var wire 1 V A $end
$var wire 1 I Y $end
$upscope $end
$scope module _30_ $end
$var wire 1 W A $end
$var wire 1 H Y $end
$upscope $end
$scope module _31_ $end
$var wire 1 X A $end
$var wire 1 G Y $end
$upscope $end
$scope module _32_ $end
$var wire 1 Y A $end
$var wire 1 F Y $end
$upscope $end
$scope module _33_ $end
$var wire 1 Z A $end
$var wire 1 E Y $end
$upscope $end
$scope module _34_ $end
$var wire 1 [ A $end
$var wire 1 D Y $end
$upscope $end
$scope module _35_ $end
$var wire 1 \ A $end
$var wire 1 C Y $end
$upscope $end
$scope module _36_ $end
$var wire 1 # B $end
$var wire 1 B Y $end
$var wire 1 & A $end
$upscope $end
$scope module _37_ $end
$var wire 1 B A $end
$var wire 1 A Y $end
$upscope $end
$scope module _38_ $end
$var wire 1 ] A $end
$var wire 1 A B $end
$var wire 1 @ Y $end
$upscope $end
$scope module _39_ $end
$var wire 1 @ A $end
$var wire 1 ^ Y $end
$upscope $end
$scope module _40_ $end
$var wire 1 _ A $end
$var wire 1 A B $end
$var wire 1 ? Y $end
$upscope $end
$scope module _41_ $end
$var wire 1 ? A $end
$var wire 1 ` Y $end
$upscope $end
$scope module _42_ $end
$var wire 1 N A $end
$var wire 1 @ B $end
$var wire 1 a Y $end
$upscope $end
$scope module _43_ $end
$var wire 1 b A $end
$var wire 1 ? B $end
$var wire 1 c Y $end
$upscope $end
$scope module _44_ $end
$var wire 1 d A $end
$var wire 1 @ B $end
$var wire 1 e Y $end
$upscope $end
$scope module _45_ $end
$var wire 1 N A $end
$var wire 1 A B $end
$var wire 1 > Y $end
$upscope $end
$scope module _46_ $end
$var wire 1 f A $end
$var wire 1 > B $end
$var wire 1 g Y $end
$upscope $end
$scope module _47_ $end
$var wire 1 # A $end
$var wire 1 M B $end
$var wire 1 = Y $end
$upscope $end
$scope module _48_ $end
$var wire 1 h A $end
$var wire 1 i B $end
$var wire 1 < Y $end
$upscope $end
$scope module _49_ $end
$var wire 1 j A $end
$var wire 1 k B $end
$var wire 1 ; Y $end
$upscope $end
$scope module _50_ $end
$var wire 1 < A $end
$var wire 1 ; B $end
$var wire 1 : Y $end
$upscope $end
$scope module _51_ $end
$var wire 1 = A $end
$var wire 1 : B $end
$var wire 1 P Y $end
$upscope $end
$scope module _52_ $end
$var wire 1 L A $end
$var wire 1 B B $end
$var wire 1 l Y $end
$upscope $end
$scope module _53_ $end
$var wire 1 K A $end
$var wire 1 B B $end
$var wire 1 m Y $end
$upscope $end
$scope module _54_ $end
$var wire 1 J A $end
$var wire 1 B B $end
$var wire 1 n Y $end
$upscope $end
$scope module _55_ $end
$var wire 1 I A $end
$var wire 1 B B $end
$var wire 1 o Y $end
$upscope $end
$scope module _56_ $end
$var wire 1 H A $end
$var wire 1 B B $end
$var wire 1 p Y $end
$upscope $end
$scope module _57_ $end
$var wire 1 G A $end
$var wire 1 B B $end
$var wire 1 q Y $end
$upscope $end
$scope module _58_ $end
$var wire 1 F A $end
$var wire 1 B B $end
$var wire 1 r Y $end
$upscope $end
$scope module _59_ $end
$var wire 1 E A $end
$var wire 1 B B $end
$var wire 1 s Y $end
$upscope $end
$scope module _60_ $end
$var wire 1 D A $end
$var wire 1 B B $end
$var wire 1 t Y $end
$upscope $end
$scope module _61_ $end
$var wire 1 C A $end
$var wire 1 B B $end
$var wire 1 u Y $end
$upscope $end
$scope module _62_ $end
$var wire 1 - C $end
$var wire 1 v D $end
$var reg 1 w Q $end
$upscope $end
$scope module _63_ $end
$var wire 1 - C $end
$var wire 1 x D $end
$var reg 1 y Q $end
$upscope $end
$scope module _64_ $end
$var wire 1 - C $end
$var wire 1 z D $end
$var reg 1 { Q $end
$upscope $end
$scope module _65_ $end
$var wire 1 - C $end
$var wire 1 | D $end
$var reg 1 } Q $end
$upscope $end
$scope module _66_ $end
$var wire 1 - C $end
$var wire 1 ~ D $end
$var reg 1 !" Q $end
$upscope $end
$scope module _67_ $end
$var wire 1 - C $end
$var wire 1 "" D $end
$var reg 1 #" Q $end
$upscope $end
$scope module _68_ $end
$var wire 1 - C $end
$var wire 1 $" D $end
$var reg 1 %" Q $end
$upscope $end
$scope module _69_ $end
$var wire 1 - C $end
$var wire 1 &" D $end
$var reg 1 '" Q $end
$upscope $end
$scope module _70_ $end
$var wire 1 - C $end
$var wire 1 (" D $end
$var reg 1 )" Q $end
$upscope $end
$scope module _71_ $end
$var wire 1 - C $end
$var wire 1 *" D $end
$var reg 1 +" Q $end
$upscope $end
$scope module _72_ $end
$var wire 1 - C $end
$var wire 1 ," D $end
$var reg 1 -" Q $end
$upscope $end
$scope module _73_ $end
$var wire 1 - C $end
$var wire 1 ." D $end
$var reg 1 /" Q $end
$upscope $end
$scope module _74_ $end
$var wire 1 - C $end
$var wire 1 P D $end
$var reg 1 & Q $end
$upscope $end
$scope module _75_ $end
$var wire 1 - C $end
$var wire 1 0" D $end
$var reg 1 1" Q $end
$upscope $end
$scope module _76_ $end
$var wire 1 - C $end
$var wire 1 2" D $end
$var reg 1 3" Q $end
$upscope $end
$scope module _77_ $end
$var wire 1 - C $end
$var wire 1 4" D $end
$var reg 1 5" Q $end
$upscope $end
$scope module _78_ $end
$var wire 1 - C $end
$var wire 1 6" D $end
$var reg 1 7" Q $end
$upscope $end
$upscope $end
$scope module arbitro_cond1 $end
$var wire 1 - clk $end
$var wire 12 8" data_in_arb [11:0] $end
$var wire 1 ) fifo_empty $end
$var wire 4 9" fifos_almost_full [3:0] $end
$var wire 1 # reset $end
$var reg 2 :" class [1:0] $end
$var reg 12 ;" data_out_arb [11:0] $end
$var reg 1 ' pop $end
$var reg 4 <" push [3:0] $end
$upscope $end
$upscope $end
$scope module DFFSR $end
$var wire 1 =" C $end
$var wire 1 >" D $end
$var wire 1 ?" R $end
$var wire 1 @" S $end
$var reg 1 A" Q $end
$upscope $end
$enddefinitions $end
#0
$dumpvars
xA"
z@"
z?"
z>"
z="
bx <"
bx ;"
b0 :"
b0 9"
b0 8"
x7"
06"
x5"
04"
x3"
02"
x1"
00"
x/"
0."
x-"
0,"
x+"
0*"
x)"
0("
x'"
0&"
x%"
0$"
x#"
0""
x!"
0~
x}
0|
x{
0z
xy
0x
xw
0v
0u
0t
0s
0r
0q
0p
0o
0n
0m
0l
0k
0j
0i
0h
0g
0f
0e
0d
0c
0b
0a
0`
0_
0^
0]
0\
0[
0Z
0Y
0X
0W
0V
0U
0T
0S
0R
b0 Q
0P
b0 O
1N
1M
1L
1K
1J
1I
1H
1G
1F
1E
1D
1C
1B
0A
1@
1?
1>
1=
1<
1;
0:
b0 9
bx 8
bx 7
b0 6
b0 5
b0 4
b0 3
bx 2
bx 1
bx 0
bz /
bx .
0-
b0 ,
bx +
bx *
0)
b0 (
x'
x&
bx %
bx $
0#
z"
z!
$end
#1
1P
0N
0L
0K
0G
0F
0E
0C
0=
b111 .
1R
1S
1T
1X
1Y
1Z
1\
1]
1_
1b
1d
1f
b11 9
b11 :"
b0 +
b0 2
b0 ;"
b0 %
b0 0
b0 <"
0'
0w
0y
0{
0}
0!"
0#"
0%"
0'"
0)"
0+"
0-"
b0 *
b0 1
b0 8
0/"
0&
01"
03"
05"
b0 $
b0 7
07"
b111011100011 ,
b111011100011 3
b111011100011 5
b111011100011 8"
1#
1-
#2
0-
#3
10"
b1 O
1g
1v
1x
1""
1$"
1&"
1*"
0>
1l
1m
1q
1r
1s
b1011100011 Q
1u
1A
1N
0B
0R
0]
0_
0b
0d
0f
b0 9
b0 :"
b1011100011 ,
b1011100011 3
b1011100011 5
b1011100011 8"
1&
1'
1-
#4
0-
#5
16"
1~
0*"
1,"
1."
1a
1>
1p
0u
1^
b110011110011 Q
1`
00"
0@
0?
b1000 O
0g
0N
0H
1C
1R
1W
0\
1]
1_
1b
1d
1f
b11 9
b11 :"
b1011100011 +
b1011100011 2
b1011100011 ;"
b1 %
b1 0
b1 <"
1w
1y
1#"
1%"
1'"
b1011100011 *
b1011100011 1
b1011100011 8
1+"
b1 $
b1 7
11"
b110011110011 ,
b110011110011 3
b110011110011 5
b110011110011 8"
1-
#6
0-
#7
06"
0x
0$"
0&"
0,"
0a
0m
0r
0s
b100000110001 Q
0^
14"
1@
b100 O
1c
1K
1F
1E
0T
0Y
0Z
0]
0b
0f
b10 9
b10 :"
b100000110001 ,
b100000110001 3
b100000110001 5
b100000110001 8"
17"
b1000 $
b1000 7
01"
1/"
1-"
0+"
b110011110011 *
b110011110011 1
b110011110011 8
1!"
b110011110011 +
b110011110011 2
b110011110011 ;"
b1000 %
b1000 0
b1000 <"
1-
#8
0-
#9
12"
1z
1|
1&"
1("
1*"
1,"
1e
0."
0>
1n
1o
1s
1t
1u
1^
b11110111101 Q
0`
04"
0@
1?
b10 O
0c
1N
0J
0I
0E
0D
0C
0R
1U
1V
1Z
1[
1\
1]
0_
1b
0d
1f
b1 9
b1 :"
b100000110001 +
b100000110001 2
b100000110001 ;"
b100 %
b100 0
b100 <"
0y
0%"
0'"
b100000110001 *
b100000110001 1
b100000110001 8
0-"
15"
b100 $
b100 7
07"
b11110111101 ,
b11110111101 3
b11110111101 5
b11110111101 8"
1-
#10
0-
#11
16"
1$"
1."
1a
1>
1r
b111111111101 Q
1`
02"
0?
b1000 O
0e
0N
0F
1R
1Y
1_
1d
b11 9
b11 :"
b111111111101 ,
b111111111101 3
b111111111101 5
b111111111101 8"
05"
b10 $
b10 7
13"
0/"
1-"
1+"
1)"
1'"
1}
b11110111101 *
b11110111101 1
b11110111101 8
1{
b11110111101 +
b11110111101 2
b11110111101 ;"
b10 %
b10 0
b10 <"
1-
#12
0-
#13
0P
1=
0M
b111111111101 +
b111111111101 2
b111111111101 ;"
b1000 %
b1000 0
b1000 <"
1%"
b111111111101 *
b111111111101 1
b111111111101 8
1/"
03"
b1000 $
b1000 7
17"
1)
1-
#14
0-
#15
0,"
0^
06"
0."
1@
0v
0z
0|
0~
0""
0$"
0&"
0("
0*"
0a
0`
02"
0l
0n
0o
0p
0q
0r
0s
0t
b0 Q
0u
1?
b0 O
0e
0A
1N
1B
0R
0_
0d
b1 9
b1 :"
b11111111101 ,
b11111111101 3
b11111111101 5
b11111111101 8"
0&
b111111111101 +
b111111111101 2
b111111111101 ;"
b1000 %
b1000 0
b1000 <"
0'
1-
#16
0-
#17
1:
0P
0;
0=
1G
1F
1k
0X
0Y
0]
0b
0f
b0 9
b0 :"
1M
b0 +
b0 2
b0 ;"
b0 %
b0 0
b0 <"
0w
0{
0}
0!"
0#"
0%"
0'"
0)"
0+"
0-"
b0 *
b0 1
b0 8
0/"
b0 $
b0 7
07"
b1 (
b1 4
b1 6
b1 9"
b1110011101 ,
b1110011101 3
b1110011101 5
b1110011101 8"
0)
1-
#18
0-
#19
0<
1;
0N
1H
1h
0k
1R
0W
1]
1_
1b
1d
1f
b11 9
b11 :"
b1000 (
b1000 4
b1000 6
b1000 9"
b111110001101 ,
b111110001101 3
b111110001101 5
b111110001101 8"
1-
#20
0-
#21
1<
0;
1N
0H
0h
1j
0R
1W
0_
0d
b1 9
b1 :"
b10 (
b10 4
b10 6
b10 9"
b11110011101 ,
b11110011101 3
b11110011101 5
b11110011101 8"
1-
#22
0-
#23
0<
1;
0N
0K
1J
0G
1C
1i
0j
1R
1T
0U
1X
0\
0]
1_
0b
1d
0f
b10 9
b10 :"
b100 (
b100 4
b100 6
b100 9"
b100110111011 ,
b100110111011 3
b100110111011 5
b100110111011 8"
1-
#24
0-
#25
0;
1h
1j
1k
b1111 (
b1111 4
b1111 6
b1111 9"
1-
